ab_testing/__init__.py
ab_testing/abtesting.py
ab_testing/data/__init__.py
ab_testing/data/dataset.py
ab_testing_analysis-1.2.8.dist-info/LICENSE
ab_testing_analysis-1.2.8.dist-info/METADATA
ab_testing_analysis-1.2.8.dist-info/WHEEL
ab_testing_analysis-1.2.8.dist-info/top_level.txt
ab_testing_analysis-1.2.8.dist-info/RECORD
