Metadata-Version: 2.1
Name: ab-testing-analysis
Version: 1.2.8
Summary: AB test analysis toolbox for analyzing and reporting the results of an ab test experiment. It provides the functions to analyze the ab test result of an experiment.
Author: Mihir Deo
Author-email: <mihirdeo16@gmail.com>
Project-URL: Homepage, https://ab-testing-analysis.readthedocs.io/en/latest/index.html
Project-URL: Documentation, https://ab-testing-analysis.readthedocs.io/en/latest/Getting_Started.html
Project-URL: Source, https://github.com/mihirdeo16/ab-testing
Project-URL: Tracker, https://github.com/mihirdeo16/ab-testing/issues
Keywords: python,ab test,ab testing,ab testing analysis,abtesting analysis,abtesting,response analysis,conversion rate analysis,statistical test
Classifier: Intended Audience :: Developers
Classifier: Intended Audience :: Science/Research
Classifier: Intended Audience :: Financial and Insurance Industry
Classifier: Intended Audience :: Healthcare Industry
Classifier: Intended Audience :: Information Technology
Classifier: License :: OSI Approved :: MIT License
Classifier: Programming Language :: Python :: 3
Classifier: Programming Language :: Python :: 3.7
Classifier: Programming Language :: Python :: 3.8
Classifier: Programming Language :: Python :: 3.9
Classifier: Operating System :: OS Independent
Classifier: Development Status :: 5 - Production/Stable
Classifier: Topic :: Scientific/Engineering :: Human Machine Interfaces
Classifier: Topic :: Scientific/Engineering :: Information Analysis
Classifier: Topic :: Scientific/Engineering :: Mathematics
Classifier: Topic :: Office/Business :: Financial :: Point-Of-Sale
License-File: LICENSE
Requires-Dist: pandas
Requires-Dist: statsmodels
